<?xml version="1.0" encoding="UTF-8"?>
<VisualHFSM><SubAutomata id="1" idFather="0"><state initial="true" id="1"><posx>61</posx><posy>101</posy><name>TakeOff</name><idSubautomataSon>2</idSubautomataSon><code>print "Taking Off"
self.lock.acquire()
self.extraPrx.takeoff()
self.lock.release()
hasTakenOff = True</code></state><state initial="false" id="2"><posx>283</posx><posy>75</posy><name>Stabilizing1</name><idSubautomataSon>0</idSubautomataSon><code>print "Stabilizing"</code></state><state initial="false" id="3"><posx>497</posx><posy>130</posy><name>GoFront</name><idSubautomataSon>0</idSubautomataSon><code>cmd = jderobot.CMDVelData()
cmd.linearX = 1
cmd.linearY = 0
cmd.linearZ = 0
self.lock.acquire()
self.cmdPrx.setCMDVelData(cmd)
self.lock.release()</code></state><state initial="false" id="4"><posx>489</posx><posy>320</posy><name>Stoping</name><idSubautomataSon>4</idSubautomataSon><code>cmd = jderobot.CMDVelData()
cmd.linearX = 0
cmd.linearY = 0
cmd.linearZ = 0
self.lock.acquire()
self.cmdPrx.setCMDVelData(cmd)
self.lock.release()
print "Stoping"</code></state><state initial="false" id="5"><posx>250</posx><posy>408</posy><name>Landing</name><idSubautomataSon>0</idSubautomataSon><code>print "Landing"
self.lock.acquire()
self.extraPrx.land()
self.lock.release()
hasLanded = True</code></state><state initial="false" id="6"><posx>66</posx><posy>283</posy><name>Stabilizing2</name><idSubautomataSon>0</idSubautomataSon><code>finished()</code></state><transition id="1"><posx>9</posx><posy>212</posy><origin>1</origin><destiny>2</destiny><transcode>print "Going to Stabilizing"</transcode><name>transition</name><trans type="condition">hasTakenOff</trans></transition><transition id="2"><posx>413</posx><posy>79</posy><origin>2</origin><destiny>3</destiny><transcode>print "going to GoFront"</transcode><name>transition</name><trans type="time">1500</trans></transition><transition id="3"><posx>570</posx><posy>239</posy><origin>3</origin><destiny>4</destiny><transcode>print "going to Stoping"</transcode><name>transition</name><trans type="time">3000</trans></transition><transition id="4"><posx>410</posx><posy>411</posy><origin>4</origin><destiny>5</destiny><transcode>print "going to Land"</transcode><name>transition</name><trans type="time">3500</trans></transition><transition id="6"><posx>152</posx><posy>338</posy><origin>5</origin><destiny>6</destiny><transcode></transcode><name>transition</name><trans type="condition">hasLanded</trans></transition><transition id="1"><posx>9</posx><posy>212</posy><origin>6</origin><destiny>1</destiny><transcode>print "Restarting"</transcode><name>transition</name><trans type="time">3000</trans></transition><iteration_time>100</iteration_time><variables>hasTakenOff = False
hasLanded = False</variables><functions>def finished():
	print "FINISHED!"</functions></SubAutomata><SubAutomata id="2" idFather="1"><state initial="false" id="6"><posx>119</posx><posy>197</posy><name>Son1</name><idSubautomataSon>3</idSubautomataSon><code>print "wait1"</code></state><state initial="true" id="7"><posx>475</posx><posy>140</posy><name>Son2</name><idSubautomataSon>0</idSubautomataSon><code>print "wait2"</code></state><state initial="false" id="8"><posx>347</posx><posy>306</posy><name>Son3</name><idSubautomataSon>0</idSubautomataSon><code>print "wait3"</code></state><transition id="1"><posx>296</posx><posy>168</posy><origin>6</origin><destiny>7</destiny><transcode></transcode><name>transition</name><trans type="time">1000</trans></transition><transition id="2"><posx>411</posx><posy>223</posy><origin>7</origin><destiny>8</destiny><transcode></transcode><name>transition</name><trans type="time">1000</trans></transition><transition id="3"><posx>233</posx><posy>252</posy><origin>8</origin><destiny>6</destiny><transcode></transcode><name>transition</name><trans type=""></trans></transition><transition id="4"><posx>233</posx><posy>252</posy><origin>8</origin><destiny>6</destiny><transcode></transcode><name>transition</name><trans type="condition">True</trans></transition><iteration_time>100</iteration_time><variables></variables><functions></functions></SubAutomata><SubAutomata id="3" idFather="2"><state initial="true" id="9"><posx>165</posx><posy>156</posy><name>SonOfSon</name><idSubautomataSon>0</idSubautomataSon><code>print "son of son"</code></state><transition id="6"><posx>165</posx><posy>196</posy><origin>9</origin><destiny>9</destiny><transcode></transcode><name></name><trans type="time">2000</trans></transition><transition id="7"><posx>165</posx><posy>256</posy><origin>9</origin><destiny>9</destiny><transcode></transcode><name></name><trans type="time">3000</trans></transition><iteration_time>100</iteration_time><variables></variables><functions></functions></SubAutomata><SubAutomata id="4" idFather="1"><state initial="false" id="10"><posx>99</posx><posy>180</posy><name>Stop2</name><idSubautomataSon>0</idSubautomataSon><code>print "wait"</code></state><state initial="true" id="11"><posx>337</posx><posy>153</posy><name>Stop1</name><idSubautomataSon>0</idSubautomataSon><code>print "wait"</code></state><transition id="5"><posx>218</posx><posy>166</posy><origin>11</origin><destiny>10</destiny><transcode></transcode><name>transition</name><trans type="time">3000</trans></transition><iteration_time>100</iteration_time><variables></variables><functions></functions></SubAutomata><libraries><lib>jderobot</lib></libraries><config><iceinterface><nameinterface>camera</nameinterface><ip>localhost</ip><port>9994</port><interface>Camera</interface></iceinterface><iceinterface><nameinterface>pose3d</nameinterface><ip>localhost</ip><port>9000</port><interface>Pose3D</interface></iceinterface><iceinterface><nameinterface>cmd</nameinterface><ip>localhost</ip><port>9850</port><interface>CMDVel</interface></iceinterface><iceinterface><nameinterface>extra</nameinterface><ip>localhost</ip><port>9701</port><interface>ArDroneExtra</interface></iceinterface><iceinterface><nameinterface>navdata</nameinterface><ip>localhost</ip><port>9700</port><interface>Navdata</interface></iceinterface></config></VisualHFSM>
