<?xml version="1.0" encoding="UTF-8"?>
<VisualHFSM><SubAutomata id="1" idFather="0"><state initial="true" id="1"><posx>80</posx><posy>160</posy><name>State1</name><idSubautomataSon>0</idSubautomataSon><code>print "State1"
time.sleep(2)</code></state><state initial="false" id="2"><posx>473</posx><posy>164</posy><name>State2</name><idSubautomataSon>0</idSubautomataSon><code>print "State2"
time.sleep(2)</code></state><state initial="false" id="3"><posx>475</posx><posy>431</posy><name>State3</name><idSubautomataSon>0</idSubautomataSon><code>print "State3"
time.sleep(2)</code></state><state initial="false" id="4"><posx>94</posx><posy>417</posy><name>State4</name><idSubautomataSon>0</idSubautomataSon><code>print "State4"
time.sleep(2)
self.finished = True</code></state><transition id="1"><posx>276</posx><posy>162</posy><origin>1</origin><destiny>2</destiny><transcode></transcode><name>trans1</name><trans type="time">2000</trans></transition><transition id="2"><posx>474</posx><posy>298</posy><origin>2</origin><destiny>3</destiny><transcode></transcode><name>trans2</name><trans type="time">2000</trans></transition><transition id="3"><posx>285</posx><posy>424</posy><origin>3</origin><destiny>4</destiny><transcode></transcode><name>trans3</name><trans type="time">2000</trans></transition><transition id="4"><posx>87</posx><posy>288</posy><origin>4</origin><destiny>1</destiny><transcode>print "Finished!"</transcode><name>LastTrans</name><trans type="condition">self.finished</trans></transition><iteration_time>100</iteration_time><variables>self.finished = False</variables><functions></functions></SubAutomata><libraries><lib>time</lib></libraries><config/></VisualHFSM>
